ethcheck/__init__.py
ethcheck/ethcheck.py
ethcheck/generate_pytest.py
ethcheck/list_forks.py
ethcheck/spec.py
ethcheck-0.1.4.data/data/bin/esbmc
ethcheck-0.1.4.dist-info/LICENSE
ethcheck-0.1.4.dist-info/METADATA
ethcheck-0.1.4.dist-info/WHEEL
ethcheck-0.1.4.dist-info/entry_points.txt
ethcheck-0.1.4.dist-info/top_level.txt
ethcheck-0.1.4.dist-info/RECORD
